{
  "meta": {
    "date": "2023-10-11",
    "location": "London",
    "composite_confidence": 8.33
  },
  "input_features": {
    "min_temp \u00b0c": 15.0,
    "max_temp \u00b0c": 25.0,
    "rain mm": 0.0,
    "humidity %": 56.0,
    "cloud_cover %": 11.0,
    "wind_speed km/h": 13.0,
    "wind_direction_numerical": 225.0,
    "day_of_year": 283.0,
    "location_code": 355.0
  },
  "variables": {
    "next_min_temp \u00b0c": {
      "prediction": 13.8912,
      "confidence": 12.64,
      "shap": {
        "base_value": 7.30719,
        "values": [
          5.769165,
          1.089763,
          0.057757,
          0.180171,
          -0.017679,
          0.024316,
          0.010044,
          -0.523429,
          -0.006071
        ],
        "features": [
          "min_temp \u00b0c",
          "max_temp \u00b0c",
          "rain mm",
          "humidity %",
          "cloud_cover %",
          "wind_speed km/h",
          "wind_direction_numerical",
          "day_of_year",
          "location_code"
        ]
      }
    },
    "next_max_temp \u00b0c": {
      "prediction": 21.3976,
      "confidence": 20.18,
      "shap": {
        "base_value": 13.175162,
        "values": [
          0.243866,
          9.239773,
          0.114812,
          0.48449,
          -0.088154,
          -0.315429,
          0.082022,
          -1.5308,
          -0.008138
        ],
        "features": [
          "min_temp \u00b0c",
          "max_temp \u00b0c",
          "rain mm",
          "humidity %",
          "cloud_cover %",
          "wind_speed km/h",
          "wind_direction_numerical",
          "day_of_year",
          "location_code"
        ]
      }
    },
    "next_rain mm": {
      "prediction": 1.6777,
      "confidence": 85.61,
      "shap": {
        "base_value": 2.447035,
        "values": [
          0.050372,
          0.186286,
          -2.118231,
          0.477165,
          0.385823,
          -0.322802,
          0.080118,
          0.490563,
          0.001417
        ],
        "features": [
          "min_temp \u00b0c",
          "max_temp \u00b0c",
          "rain mm",
          "humidity %",
          "cloud_cover %",
          "wind_speed km/h",
          "wind_direction_numerical",
          "day_of_year",
          "location_code"
        ]
      }
    },
    "next_humidity %": {
      "prediction": 65.418,
      "confidence": 15.98,
      "shap": {
        "base_value": 81.284088,
        "values": [
          -1.161491,
          -0.159736,
          -0.088491,
          -17.346131,
          -0.017326,
          1.133981,
          0.599404,
          1.175597,
          -0.001901
        ],
        "features": [
          "min_temp \u00b0c",
          "max_temp \u00b0c",
          "rain mm",
          "humidity %",
          "cloud_cover %",
          "wind_speed km/h",
          "wind_direction_numerical",
          "day_of_year",
          "location_code"
        ]
      }
    },
    "next_cloud_cover %": {
      "prediction": 37.2846,
      "confidence": 24.45,
      "shap": {
        "base_value": 57.092567,
        "values": [
          -1.673899,
          -2.331547,
          -0.714708,
          -0.729044,
          -18.423986,
          1.75347,
          0.911423,
          1.406272,
          -0.0059
        ],
        "features": [
          "min_temp \u00b0c",
          "max_temp \u00b0c",
          "rain mm",
          "humidity %",
          "cloud_cover %",
          "wind_speed km/h",
          "wind_direction_numerical",
          "day_of_year",
          "location_code"
        ]
      }
    },
    "next_wind_speed km/h": {
      "prediction": 15.9327,
      "confidence": 32.6,
      "shap": {
        "base_value": 16.659684,
        "values": [
          0.227372,
          -0.861257,
          0.032628,
          -0.430839,
          0.881416,
          -1.91006,
          0.71207,
          0.622637,
          -0.00098
        ],
        "features": [
          "min_temp \u00b0c",
          "max_temp \u00b0c",
          "rain mm",
          "humidity %",
          "cloud_cover %",
          "wind_speed km/h",
          "wind_direction_numerical",
          "day_of_year",
          "location_code"
        ]
      }
    },
    "next_wind_direction_numerical": {
      "prediction": 108.0735,
      "confidence": 0.0,
      "shap": {
        "base_value": 201.403565,
        "values": [
          -2.237499,
          -13.552578,
          -1.72445,
          -0.499586,
          -23.246587,
          -13.148027,
          -5.563502,
          -33.319436,
          -0.038352
        ],
        "features": [
          "min_temp \u00b0c",
          "max_temp \u00b0c",
          "rain mm",
          "humidity %",
          "cloud_cover %",
          "wind_speed km/h",
          "wind_direction_numerical",
          "day_of_year",
          "location_code"
        ]
      }
    }
  }
}